protolingo/__init__.py
protolingo/__main__.py
protolingo/utils.py
protolingo/semantics/Expression.py
protolingo/semantics/__init__.py
protolingo/syntax/Graph.py
protolingo/syntax/Node.py
protolingo/syntax/__init__.py
protolingo/vernacular/Shell.py
protolingo/vernacular/__init__.py
protolingo/yaml/Parser.py
protolingo/yaml/YAMLDoc.py
protolingo/yaml/YAMLExpression.py
protolingo/yaml/__init__.py
protolingo-0.0.5.dist-info/LICENSE
protolingo-0.0.5.dist-info/METADATA
protolingo-0.0.5.dist-info/WHEEL
protolingo-0.0.5.dist-info/top_level.txt
protolingo-0.0.5.dist-info/RECORD
