Metadata-Version: 2.1
Name: protolingo
Version: 0.0.5
Summary: Meta-language Framework
Home-page: https://github.com/dialectsoftware/protolingo
Author: Dialect Software LLC
Author-email: support@dialectsoftware.com
License: UNKNOWN
Platform: UNKNOWN
Classifier: Programming Language :: Python :: 3.6
Classifier: License :: OSI Approved :: MIT License
Classifier: Operating System :: OS Independent
Requires-Dist: Pykka
Requires-Dist: jinja2
Requires-Dist: PyYAML
